jdDiff/AboutDialog.py
jdDiff/BrowseDialog.py
jdDiff/CompareThread.py
jdDiff/Enviroment.py
jdDiff/Functions.py
jdDiff/Icon.svg
jdDiff/MainWindow.py
jdDiff/Settings.py
jdDiff/SettingsDialog.py
jdDiff/__init__.py
jdDiff/version.txt
jdDiff/translations/jdDiff_de.qm
jdDiff/translations/jdDiff_nl.qm
jdDiff/translations/jdDiff_sv.qm
jdDiff/ui_compiled/AboutDialog.py
jdDiff/ui_compiled/BrowseDialog.py
jdDiff/ui_compiled/MainWindow.py
jdDiff/ui_compiled/SettingsDialog.py
jdDiff/ui_compiled/__init__.py
jdDiff-1.4.dist-info/LICENSE
jdDiff-1.4.dist-info/METADATA
jdDiff-1.4.dist-info/WHEEL
jdDiff-1.4.dist-info/entry_points.txt
jdDiff-1.4.dist-info/top_level.txt
jdDiff-1.4.dist-info/RECORD
