Metadata-Version: 2.1
Name: jdDiff
Version: 1.4
Summary: A graphical cross platform diff viewer
Author-email: JakobDev <jakobdev@gmx.de>
License: GPL v3
Project-URL: Translate, https://translate.codeberg.org/projects/jdDiff
Project-URL: Issues, https://gitlab.com/JakobDev/jdDiff/-/issues
Project-URL: Source, https://gitlab.com/JakobDev/jdDiff
Project-URL: Donation, https://ko-fi.com/jakobdev
Keywords: JakobDev,PyQt
Classifier: Development Status :: 5 - Production/Stable
Classifier: Intended Audience :: End Users/Desktop
Classifier: Environment :: Other Environment
Classifier: Environment :: X11 Applications :: Qt
Classifier: License :: OSI Approved :: GNU General Public License v3 (GPLv3)
Classifier: Natural Language :: English
Classifier: Natural Language :: German
Classifier: Topic :: Software Development
Classifier: Topic :: Utilities
Classifier: Operating System :: OS Independent
Classifier: Operating System :: POSIX
Classifier: Operating System :: POSIX :: Linux
Classifier: Operating System :: MacOS :: MacOS X
Classifier: Operating System :: Microsoft :: Windows
Classifier: Programming Language :: Python :: 3
Classifier: Programming Language :: Python :: 3.9
Classifier: Programming Language :: Python :: 3.10
Classifier: Programming Language :: Python :: 3.11
Classifier: Programming Language :: Python :: 3 :: Only
Classifier: Programming Language :: Python :: Implementation :: CPython
Requires-Python: >=3.9
License-File: LICENSE
Requires-Dist: PyQt6
